cli/__init__.py
cli/cli.py
techtonique_cli-0.2.0.dist-info/METADATA
techtonique_cli-0.2.0.dist-info/WHEEL
techtonique_cli-0.2.0.dist-info/entry_points.txt
techtonique_cli-0.2.0.dist-info/top_level.txt
techtonique_cli-0.2.0.dist-info/RECORD
