Metadata-Version: 2.2
Name: techtonique_cli
Version: 0.2.0
Summary: A CLI tool for Techtonique API
Home-page: https://github.com/Techtonique/cli/
Author: Techtonique
Author-email: support@techtonique.net
Classifier: Programming Language :: Python :: 3
Classifier: License :: OSI Approved :: MIT License
Classifier: Operating System :: OS Independent
Requires-Python: >=3.6
Requires-Dist: click>=8.0.0
Requires-Dist: requests>=2.0.0
Dynamic: author
Dynamic: author-email
Dynamic: classifier
Dynamic: description
Dynamic: description-content-type
Dynamic: home-page
Dynamic: requires-dist
Dynamic: requires-python
Dynamic: summary
